aliyunsdkcloudesl/__init__.py
aliyunsdkcloudesl/endpoint.py
aliyunsdkcloudesl/request/__init__.py
aliyunsdkcloudesl/request/v20200201/ActivateApDeviceRequest.py
aliyunsdkcloudesl/request/v20200201/AddApDeviceRequest.py
aliyunsdkcloudesl/request/v20200201/AddCompanyTemplateRequest.py
aliyunsdkcloudesl/request/v20200201/AddMaterialRequest.py
aliyunsdkcloudesl/request/v20200201/AddUserRequest.py
aliyunsdkcloudesl/request/v20200201/ApplyCompanyTemplateVersionToStoresRequest.py
aliyunsdkcloudesl/request/v20200201/ApplyImageDitheringRequest.py
aliyunsdkcloudesl/request/v20200201/AssignUserRequest.py
aliyunsdkcloudesl/request/v20200201/BatchInsertItemsRequest.py
aliyunsdkcloudesl/request/v20200201/BatchUpdateEventRequest.py
aliyunsdkcloudesl/request/v20200201/BindDeviceLayoutRequest.py
aliyunsdkcloudesl/request/v20200201/BindEslDeviceRequest.py
aliyunsdkcloudesl/request/v20200201/CheckServiceLinkedRoleForDeletingRequest.py
aliyunsdkcloudesl/request/v20200201/CopyCompanyTemplateViewRequest.py
aliyunsdkcloudesl/request/v20200201/CopyLayoutRequest.py
aliyunsdkcloudesl/request/v20200201/CopyTemplateGroupRequest.py
aliyunsdkcloudesl/request/v20200201/CreateStoreRequest.py
aliyunsdkcloudesl/request/v20200201/DeleteApDeviceRequest.py
aliyunsdkcloudesl/request/v20200201/DeleteCompanyTemplateRequest.py
aliyunsdkcloudesl/request/v20200201/DeleteItemRequest.py
aliyunsdkcloudesl/request/v20200201/DeleteLayoutRequest.py
aliyunsdkcloudesl/request/v20200201/DeleteMaterialRequest.py
aliyunsdkcloudesl/request/v20200201/DeleteStoreRequest.py
aliyunsdkcloudesl/request/v20200201/DeleteTemplateGroupRequest.py
aliyunsdkcloudesl/request/v20200201/DeleteUserRequest.py
aliyunsdkcloudesl/request/v20200201/DescribeApDevicesRequest.py
aliyunsdkcloudesl/request/v20200201/DescribeAvailableEslModelsRequest.py
aliyunsdkcloudesl/request/v20200201/DescribeBindersRequest.py
aliyunsdkcloudesl/request/v20200201/DescribeCompanyTemplateAttributeRequest.py
aliyun_python_sdk_cloudesl-2.1.1.dist-info/LICENSE
aliyun_python_sdk_cloudesl-2.1.1.dist-info/METADATA
aliyun_python_sdk_cloudesl-2.1.1.dist-info/WHEEL
aliyun_python_sdk_cloudesl-2.1.1.dist-info/top_level.txt
aliyun_python_sdk_cloudesl-2.1.1.dist-info/RECORD
